segmentedcreator/__init__.py
segmentedcreator/class_dict.csv
segmentedcreator/eighth_step.py
segmentedcreator/fifth_step.py
segmentedcreator/first_step.py
segmentedcreator/forest-dark.tcl
segmentedcreator/fourth_step.py
segmentedcreator/guimain.py
segmentedcreator/second_step.py
segmentedcreator/seventh_step.py
segmentedcreator/sixth_step.py
segmentedcreator/third_step.py
segmentedcreator/tooldata.py
segmentedcreator/forest-dark/border-accent-hover.png
segmentedcreator/forest-dark/border-accent.png
segmentedcreator/forest-dark/border-basic.png
segmentedcreator/forest-dark/border-hover.png
segmentedcreator/forest-dark/border-invalid.png
segmentedcreator/forest-dark/card.png
segmentedcreator/forest-dark/check-accent.png
segmentedcreator/forest-dark/check-basic.png
segmentedcreator/forest-dark/check-hover.png
segmentedcreator/forest-dark/check-tri-accent.png
segmentedcreator/forest-dark/check-tri-basic.png
segmentedcreator/forest-dark/check-tri-hover.png
segmentedcreator/forest-dark/check-unsel-accent.png
segmentedcreator/forest-dark/check-unsel-basic.png
segmentedcreator/forest-dark/check-unsel-hover.png
segmentedcreator/forest-dark/check-unsel-pressed.png
segmentedcreator/forest-dark/combo-button-basic.png
segmentedcreator/forest-dark/combo-button-focus.png
segmentedcreator/forest-dark/combo-button-hover.png
segmentedcreator/forest-dark/down.png
segmentedcreator/forest-dark/empty.png
segmentedcreator/forest-dark/hor-accent.png
segmentedcreator/forest-dark/hor-basic.png
segmentedcreator/forest-dark/hor-hover.png
segmentedcreator/forest-dark/notebook.png
segmentedcreator/forest-dark/off-accent.png
segmentedcreator/forest-dark/off-basic.png
segmentedcreator/forest-dark/off-hover.png
segmentedcreator/forest-dark/on-accent.png
segmentedcreator/forest-dark/on-basic.png
segmentedcreator/forest-dark/on-hover.png
segmentedcreator/forest-dark/radio-accent.png
segmentedcreator/forest-dark/radio-basic.png
segmentedcreator/forest-dark/radio-hover.png
segmented_creator-0.1.28.dist-info/METADATA
segmented_creator-0.1.28.dist-info/WHEEL
segmented_creator-0.1.28.dist-info/entry_points.txt
segmented_creator-0.1.28.dist-info/top_level.txt
segmented_creator-0.1.28.dist-info/RECORD
