Metadata-Version: 2.4
Name: segmented-creator
Version: 0.1.28
Summary: Add description
Author-email: "Miguel S. Soriano-García, Diego Mercado-Ravell, Israel Becerra, Julio De La Torre-Vanegas" <m16soriano@gmail.com>
License-Expression: MIT
Classifier: Development Status :: 3 - Alpha
Classifier: Intended Audience :: Developers
Classifier: Intended Audience :: Science/Research
Classifier: Programming Language :: Python :: 3
Classifier: Programming Language :: Python :: 3.12
Classifier: Operating System :: OS Independent
Classifier: Topic :: Scientific/Engineering :: Artificial Intelligence
Classifier: Topic :: Software Development :: Libraries :: Python Modules
Requires-Python: >=3.11
Requires-Dist: antlr4-python3-runtime>=4.9.3
Requires-Dist: anyio>=4.9.0
Requires-Dist: argon2-cffi>=25.1.0
Requires-Dist: argon2-cffi-bindings>=21.2.0
Requires-Dist: arrow>=1.3.0
Requires-Dist: asttokens>=3.0.0
Requires-Dist: async-lru>=2.0.5
Requires-Dist: attrs>=25.3.0
Requires-Dist: babel>=2.17.0
Requires-Dist: beautifulsoup4>=4.13.4
Requires-Dist: bleach>=6.2.0
Requires-Dist: certifi>=2025.6.15
Requires-Dist: cffi>=1.17.1
Requires-Dist: charset-normalizer>=3.4.2
Requires-Dist: click>=8.2.1
Requires-Dist: colorama>=0.4.6
Requires-Dist: comm>=0.2.2
Requires-Dist: contourpy>=1.3.2
Requires-Dist: cycler>=0.12.1
Requires-Dist: debugpy>=1.8.14
Requires-Dist: decorator>=5.2.1
Requires-Dist: deep-sort-realtime>=1.3.2
Requires-Dist: defusedxml>=0.7.1
Requires-Dist: eva-decord>=0.6.1
Requires-Dist: executing>=2.2.0
Requires-Dist: fastjsonschema>=2.21.1
Requires-Dist: filelock>=3.13.1
Requires-Dist: fire>=0.7.0
Requires-Dist: fonttools>=4.58.4
Requires-Dist: fqdn>=1.5.1
Requires-Dist: fsspec>=2024.6.1
Requires-Dist: h11>=0.16.0
Requires-Dist: httpcore>=1.0.9
Requires-Dist: httpx>=0.28.1
Requires-Dist: hydra-core>=1.3.2
Requires-Dist: idna>=3.10
Requires-Dist: iopath>=0.1.10
Requires-Dist: ipykernel>=6.29.5
Requires-Dist: ipython>=9.3.0
Requires-Dist: ipython_pygments_lexers>=1.1.1
Requires-Dist: ipywidgets>=8.1.7
Requires-Dist: isoduration>=20.11.0
Requires-Dist: jedi>=0.19.2
Requires-Dist: Jinja2>=3.1.4
Requires-Dist: json5>=0.12.0
Requires-Dist: jsonpointer>=3.0.0
Requires-Dist: jsonschema>=4.24.0
Requires-Dist: jsonschema-specifications>=2025.4.1
Requires-Dist: jupyter>=1.1.1
Requires-Dist: jupyter-console>=6.6.3
Requires-Dist: jupyter-events>=0.12.0
Requires-Dist: jupyter-lsp>=2.2.5
Requires-Dist: jupyter_client>=8.6.3
Requires-Dist: jupyter_core>=5.8.1
Requires-Dist: jupyter_server>=2.16.0
Requires-Dist: jupyter_server_terminals>=0.5.3
Requires-Dist: jupyterlab>=4.4.3
Requires-Dist: jupyterlab_pygments>=0.3.0
Requires-Dist: jupyterlab_server>=2.27.3
Requires-Dist: jupyterlab_widgets>=3.0.15
Requires-Dist: kiwisolver>=1.4.8
Requires-Dist: MarkupSafe>=2.1.5
Requires-Dist: matplotlib>=3.10.3
Requires-Dist: matplotlib-inline>=0.1.7
Requires-Dist: mistune>=3.1.3
Requires-Dist: mpmath>=1.3.0
Requires-Dist: nbclient>=0.10.2
Requires-Dist: nbconvert>=7.16.6
Requires-Dist: nbformat>=5.10.4
Requires-Dist: nest-asyncio>=1.6.0
Requires-Dist: networkx>=3.3
Requires-Dist: notebook>=7.4.3
Requires-Dist: notebook_shim>=0.2.4
Requires-Dist: numpy>=2.3.1
Requires-Dist: omegaconf>=2.3.0
Requires-Dist: opencv-python>=4.11.0.86
Requires-Dist: overrides>=7.7.0
Requires-Dist: packaging>=25.0
Requires-Dist: pandas>=2.3.0
Requires-Dist: pandocfilters>=1.5.1
Requires-Dist: parso>=0.8.4
Requires-Dist: pillow>=11.0.0
Requires-Dist: platformdirs>=4.3.8
Requires-Dist: portalocker>=3.2.0
Requires-Dist: prometheus_client>=0.22.1
Requires-Dist: prompt_toolkit>=3.0.51
Requires-Dist: psutil>=7.0.0
Requires-Dist: pure_eval>=0.2.3
Requires-Dist: py-cpuinfo>=9.0.0
Requires-Dist: pybboxes>=0.1.6
Requires-Dist: pycparser>=2.22
Requires-Dist: Pygments>=2.19.2
Requires-Dist: pyparsing>=3.2.3
Requires-Dist: python-dateutil>=2.9.0.post0
Requires-Dist: python-json-logger>=3.3.0
Requires-Dist: pytz>=2025.2
Requires-Dist: PyYAML>=6.0.2
Requires-Dist: pyzmq>=27.0.0
Requires-Dist: referencing>=0.36.2
Requires-Dist: requests>=2.32.4
Requires-Dist: rfc3339-validator>=0.1.4
Requires-Dist: rfc3986-validator>=0.1.1
Requires-Dist: rpds-py>=0.25.1
Requires-Dist: sahi>=0.11.27
Requires-Dist: scipy>=1.16.0
Requires-Dist: Send2Trash>=1.8.3
Requires-Dist: setuptools>=70.2.0
Requires-Dist: shapely>=2.1.1
Requires-Dist: six>=1.17.0
Requires-Dist: sniffio>=1.3.1
Requires-Dist: soupsieve>=2.7
Requires-Dist: stack-data>=0.6.3
Requires-Dist: sympy>=1.13.3
Requires-Dist: termcolor>=3.1.0
Requires-Dist: terminado>=0.18.1
Requires-Dist: terminaltables>=3.1.10
Requires-Dist: tinycss2>=1.4.0
Requires-Dist: tornado>=6.5.1
Requires-Dist: tqdm>=4.67.1
Requires-Dist: traitlets>=5.14.3
Requires-Dist: types-python-dateutil>=2.9.0.20250516
Requires-Dist: typing_extensions>=4.12.2
Requires-Dist: tzdata>=2025.2
Requires-Dist: ultralytics>=8.3.160
Requires-Dist: ultralytics-thop>=2.0.14
Requires-Dist: uri-template>=1.3.0
Requires-Dist: urllib3>=2.5.0
Requires-Dist: wcwidth>=0.2.13
Requires-Dist: webcolors>=24.11.1
Requires-Dist: webencodings>=0.5.1
Requires-Dist: websocket-client>=1.8.0
Requires-Dist: widgetsnbextension>=4.0.14
